main.py
hmt_py-0.0.1.dist-info/licenses/LICENSE
hmt_py-0.0.1.dist-info/METADATA
hmt_py-0.0.1.dist-info/WHEEL
hmt_py-0.0.1.dist-info/top_level.txt
hmt_py-0.0.1.dist-info/RECORD
