Metadata-Version: 2.4
Name: hmt_py
Version: 0.0.1
Summary: A Python library for working with the Homer Multitext project's archive.
Requires-Python: >=3.14
License-File: LICENSE
Dynamic: license-file
